config.py
main.py
start_web_config.py
web_config.py
tools/__init__.py
tools/command_execute.py
tools/file_download.py
tools/plugin_search.py
tools/web_fetch.py
tools/__pycache__/__init__.cpython-312.pyc
tools/__pycache__/__init__.cpython-313.pyc
tools/__pycache__/__init__.cpython-39.pyc
tools/__pycache__/command_execute.cpython-312.pyc
tools/__pycache__/command_execute.cpython-313.pyc
tools/__pycache__/file_download.cpython-312.pyc
tools/__pycache__/file_download.cpython-313.pyc
tools/__pycache__/minecraft_tools.cpython-312.pyc
tools/__pycache__/minecraft_tools.cpython-313.pyc
tools/__pycache__/plugin_search.cpython-312.pyc
tools/__pycache__/plugin_search.cpython-313.pyc
tools/__pycache__/web_fetch.cpython-312.pyc
tools/__pycache__/web_fetch.cpython-313.pyc
minecraft_mcp_server-1.0.2.dist-info/METADATA
minecraft_mcp_server-1.0.2.dist-info/WHEEL
minecraft_mcp_server-1.0.2.dist-info/entry_points.txt
minecraft_mcp_server-1.0.2.dist-info/top_level.txt
minecraft_mcp_server-1.0.2.dist-info/RECORD
