Metadata-Version: 2.1
Name: minecraft-mcp-server
Version: 1.0.2
Summary: Minecraft MCP Server
Home-page: https://github.com/haishen668/minecraft_mcp_server
Author: haishen668
Author-email: 2821396723@qq.com
License: UNKNOWN
Platform: UNKNOWN
Classifier: Programming Language :: Python :: 3
Classifier: License :: OSI Approved :: MIT License
Classifier: Operating System :: OS Independent
Requires-Python: >=3.8
Requires-Dist: mcp>=1.0.0
Requires-Dist: mcrcon>=0.7.0
Requires-Dist: Flask>=2.3.0
Requires-Dist: Flask-CORS>=4.0.0
Requires-Dist: python-dotenv>=1.0.0
Requires-Dist: requests>=2.31.0
Requires-Dist: beautifulsoup4>=4.12.0
Requires-Dist: markdownify>=0.11.6
Requires-Dist: readabilipy>=0.2.0
Requires-Dist: protego>=0.2.4
